LICENSE
MANIFEST.in
README
setup.py
aiosqlite/__init__.py
aiosqlite/core.py
aiosqlite_fork.egg-info/PKG-INFO
aiosqlite_fork.egg-info/SOURCES.txt
aiosqlite_fork.egg-info/dependency_links.txt
aiosqlite_fork.egg-info/top_level.txt