Metadata-Version: 1.1
Name: aiosqlite-fork
Version: 0.2.1
Summary: asyncio bridge to the standard sqlite3 module
Home-page: https://github.com/jreese/aiosqlite
Author: John Reese
Author-email: john@noswap.com
License: MIT License
Platform: UNKNOWN
Classifier: Development Status :: 4 - Beta
Classifier: Framework :: AsyncIO
Classifier: Intended Audience :: Developers
Classifier: License :: OSI Approved :: MIT License
Classifier: Programming Language :: Python
Classifier: Programming Language :: Python :: 3
Classifier: Programming Language :: Python :: 3.5
Classifier: Programming Language :: Python :: 3.6
Classifier: Topic :: Software Development :: Libraries
